microraiden/__init__.py
microraiden/click_helpers.py
microraiden/close_all_channels.py
microraiden/config.py
microraiden/exceptions.py
microraiden/header.py
microraiden/make_helpers.py
microraiden/channel_manager/__init__.py
microraiden/channel_manager/blockchain.py
microraiden/channel_manager/channel.py
microraiden/channel_manager/manager.py
microraiden/channel_manager/state.py
microraiden/client/__init__.py
microraiden/client/channel.py
microraiden/client/client.py
microraiden/client/context.py
microraiden/client/default_http_client.py
microraiden/client/http_client.py
microraiden/data/contracts.json
microraiden/examples/__init__.py
microraiden/examples/echo_client.py
microraiden/examples/echo_server.py
microraiden/examples/eth_ticker.py
microraiden/examples/m2m_client.py
microraiden/examples/stats_client.py
microraiden/examples/ticker_proxy.py
microraiden/examples/wikipaydia.py
microraiden/proxy/__init__.py
microraiden/proxy/gevent_error_patch.py
microraiden/proxy/paywalled_proxy.py
microraiden/proxy/resources/__init__.py
microraiden/proxy/resources/expensive.py
microraiden/proxy/resources/login.py
microraiden/proxy/resources/management.py
microraiden/proxy/resources/paywall_decorator.py
microraiden/proxy/resources/proxy_url.py
microraiden/requests/__init__.py
microraiden/test/__init__.py
microraiden/test/config.py
microraiden/test/conftest.py
microraiden/test/test_accept_html.py
microraiden/test/test_broke_proxy.py
microraiden/test/test_channel_manager.py
microraiden/test/test_channel_manager_db.py
microraiden/test/test_client.py
microraiden/test/test_close_all_channels.py
microraiden/test/test_contract.py
microraiden/test/test_crypto.py
microraiden/test/test_eth_ticker.py
microraiden/test/test_headers.py
microraiden/test/test_http_client.py
microraiden/test/test_performance.py
microraiden/test/test_proxy.py
microraiden/test/test_rest_api.py
microraiden/test/test_sqlite_types.py
microraiden-0.0.5.dist-info/DESCRIPTION.rst
microraiden-0.0.5.dist-info/METADATA
microraiden-0.0.5.dist-info/RECORD
microraiden-0.0.5.dist-info/WHEEL
microraiden-0.0.5.dist-info/metadata.json
microraiden-0.0.5.dist-info/top_level.txt
