Metadata-Version: 2.0
Name: microraiden
Version: 0.0.5
Summary: µRaiden is an off-chain, cheap, scalable and low-latency micropayment solution.
Home-page: https://github.com/raiden-network/microraiden
Author: Brainbot AG
Author-email: info@brainbot.com
License: BSD
Keywords: raiden ethereum microraiden blockchain
Platform: UNKNOWN
Classifier: Development Status :: 3 - Alpha
Classifier: Intended Audience :: Developers
Classifier: License :: OSI Approved :: BSD License
Classifier: Natural Language :: English
Classifier: Programming Language :: Python :: 3
Classifier: Programming Language :: Python :: 3.4
Requires-Dist: ethereum-utils (<0.5.0)
Requires-Dist: ethereum-abi-utils (==0.4.0)
Requires-Dist: coincurve
Requires-Dist: rlp (<0.6.0,>=0.4.3)
Requires-Dist: flask
Requires-Dist: flask-httpauth
Requires-Dist: flask-restful
Requires-Dist: ethereum (<2.0.0,>=1.6.1)
Requires-Dist: web3 (==3.11.1)
Requires-Dist: gevent
Requires-Dist: click
Requires-Dist: requests
Requires-Dist: werkzeug
Requires-Dist: populus (==1.9.1)
Requires-Dist: munch
Requires-Dist: typing
Requires-Dist: bs4
Requires-Dist: filelock
Requires-Dist: pytest
Requires-Dist: ethereum-tester
Requires-Dist: mock
Requires-Dist: requests-mock
